{
  "name": "Wearabouts",
  "version": "0.1",
  "author": "Brad Campbell",
  "description": "
Wearabouts Accessor
===========================

Get list of people in the room.
",
  "ports": [
              {
                "direction": "output",
                "name": "People",
                "description": "The people in the room."
              },
              {
                "direction": "input",
                "name": "Update",
                "type": "button"
              }
  ],

  "parameters": [
              {
                "name": "gatd_url",
                "required": true
              },
              {
                "name": "profile_id",
                "required": true
              },
              {
                "name": "location",
                "required": true
              }
  ],

  "code": {
            "javascript": {
                            "include": ["Wearabouts.js"]
                          }
          }
}